HackathonToolkit/__init__.py
HackathonToolkit-0.0.6.dist-info/LICENCE.txt
HackathonToolkit-0.0.6.dist-info/METADATA
HackathonToolkit-0.0.6.dist-info/WHEEL
HackathonToolkit-0.0.6.dist-info/top_level.txt
HackathonToolkit-0.0.6.dist-info/RECORD
