Metadata-Version: 2.1
Name: HackathonToolkit
Version: 0.0.6
Summary: The Hackathon Toolkit simplifies hackathon projects with utilities for setup, API interaction, data handling, ML, visualization, collaboration, and deployment, automating tasks for innovation focus.
Home-page: 
Author: Moutasim Qazi
Author-email: moutasimqazi@gmail.com
License: MIT
Keywords: hackathon,toolkit,python,library
Classifier: Development Status :: 4 - Beta
Classifier: Intended Audience :: Developers
Classifier: License :: OSI Approved :: MIT License
Classifier: Programming Language :: Python :: 3
Classifier: Programming Language :: Python :: 3.6
Classifier: Programming Language :: Python :: 3.7
Classifier: Programming Language :: Python :: 3.8
Classifier: Programming Language :: Python :: 3.9
Classifier: Programming Language :: Python :: 3.10
Classifier: Programming Language :: Python :: 3.11
License-File: LICENCE.txt
Requires-Dist: flask
Requires-Dist: pandas
Requires-Dist: tensorflow
Requires-Dist: torch
Requires-Dist: transformers
Requires-Dist: keras
Requires-Dist: torchvision
Requires-Dist: scikit-learn
Requires-Dist: seaborn
Requires-Dist: matplotlib
Requires-Dist: gitpython
Requires-Dist: boto3
Requires-Dist: google-cloud-container
Requires-Dist: google-auth
Requires-Dist: bs4
Requires-Dist: jedi
